num2geotext/__init__.py
num2geotext/float_num_to_geo_currency.py
num2geotext/float_num_to_geo_text.py
num2geotext/int_num_to_geo_text.py
num2geotext/number_to_word.py
tests/__init__.py
tests/test_float_to_currency.py
tests/test_float_to_text.py
tests/test_int_to_text.py
num2geotext-0.0.1.dist-info/LICENSE.txt
num2geotext-0.0.1.dist-info/METADATA
num2geotext-0.0.1.dist-info/WHEEL
num2geotext-0.0.1.dist-info/top_level.txt
num2geotext-0.0.1.dist-info/RECORD
